// class version 50.0 (50)
// access flags 0x21
public class test/infrastructure/ClaimApprovalRequest {

  // compiled from: ClaimApprovalRequest.java

  // access flags 0x1
  public Ljava/lang/Integer; amount

  // access flags 0x1
  public Ljava/lang/String; region

  // access flags 0x1
  public Ljava/lang/Integer; prio

  // access flags 0x1
  public Ljava/util/Date; activateAt

  // access flags 0x1
  public Ltest/infrastructure/Cust; cust

  // access flags 0x1
  public <init>()V
   L0
    LINENUMBER 5 L0
    ALOAD 0
    INVOKESPECIAL java/lang/Object.<init> ()V
   L1
    LINENUMBER 6 L1
    ALOAD 0
    SIPUSH 2000
    INVOKESTATIC java/lang/Integer.valueOf (I)Ljava/lang/Integer;
    PUTFIELD test/infrastructure/ClaimApprovalRequest.amount : Ljava/lang/Integer;
   L2
    LINENUMBER 7 L2
    ALOAD 0
    LDC "regionalClerks"
    PUTFIELD test/infrastructure/ClaimApprovalRequest.region : Ljava/lang/String;
   L3
    LINENUMBER 8 L3
    ALOAD 0
    ICONST_2
    INVOKESTATIC java/lang/Integer.valueOf (I)Ljava/lang/Integer;
    PUTFIELD test/infrastructure/ClaimApprovalRequest.prio : Ljava/lang/Integer;
   L4
    LINENUMBER 9 L4
    ALOAD 0
    NEW java/util/Date
    DUP
    INVOKESPECIAL java/util/Date.<init> ()V
    PUTFIELD test/infrastructure/ClaimApprovalRequest.activateAt : Ljava/util/Date;
   L5
    LINENUMBER 10 L5
    ALOAD 0
    NEW test/infrastructure/Cust
    DUP
    INVOKESPECIAL test/infrastructure/Cust.<init> ()V
    PUTFIELD test/infrastructure/ClaimApprovalRequest.cust : Ltest/infrastructure/Cust;
   L6
    LINENUMBER 5 L6
    RETURN
   L7
    LOCALVARIABLE this Ltest/infrastructure/ClaimApprovalRequest; L0 L7 0
    MAXSTACK = 3
    MAXLOCALS = 1
}
